swingutils/__init__.py
swingutils/beans.py
swingutils/format.py
swingutils/preferences.py
swingutils/resources.py
swingutils/events.py
swingutils/binding/__init__.py
swingutils/binding/parser.py
swingutils/binding/adapters/__init__.py
swingutils/binding/adapters/swing.py
swingutils/dialogs/__init__.py
swingutils/dialogs/basic.py
swingutils/dialogs/filechooser.py
swingutils/models/__init__.py
swingutils/models/combobox.py
swingutils/models/list.py
swingutils/models/table.py
swingutils/thirdparty/__init__.py
swingutils/thirdparty/jformdesigner.py
swingutils/threads/__init__.py
swingutils/threads/swing.py
swingutils/threads/threadpool.py
swingutils/threads/coroutine.py
swingutils/threads/util.py
jython_swingutils-2.1.2.dist-info/top_level.txt
jython_swingutils-2.1.2.dist-info/METADATA
jython_swingutils-2.1.2.dist-info/DESCRIPTION.rst
jython_swingutils-2.1.2.dist-info/metadata.json
jython_swingutils-2.1.2.dist-info/WHEEL
jython_swingutils-2.1.2.dist-info/RECORD
