Metadata-Version: 2.0
Name: jython-swingutils
Version: 2.1.2
Summary: Makes using Java's Swing UI toolkit easy on Jython
Home-page: http://pypi.python.org/jython-swingutils/
Author: Alex Gronholm
Author-email: alex.gronholm+pypi@nextday.fi
License: MIT
Keywords: jython swing
Platform: UNKNOWN
Classifier: Development Status :: 5 - Production/Stable
Classifier: Intended Audience :: Developers
Classifier: License :: OSI Approved :: MIT License
Classifier: Programming Language :: Python
Classifier: Programming Language :: Python :: 2.7
Classifier: Programming Language :: Python :: Implementation :: Jython
Classifier: Topic :: Software Development :: User Interfaces
Requires-Dist: futures (>=2.2.0)
